pygl/__init__.py
pygl/dms.cpython-37m-darwin.so
pygl/solvers.cpython-37m-darwin.so
pygl/utils.cpython-37m-darwin.so
pygl-2.0.9.dist-info/LICENSE
pygl-2.0.9.dist-info/METADATA
pygl-2.0.9.dist-info/WHEEL
pygl-2.0.9.dist-info/top_level.txt
pygl-2.0.9.dist-info/RECORD
